pypolymix/__init__.py
pypolymix/parameter_groups/__init__.py
pypolymix/parameter_groups/base.py
pypolymix/parameter_groups/deterministic.py
pypolymix/parameter_groups/gaussian.py
pypolymix/priors/__init__.py
pypolymix/priors/base.py
pypolymix/priors/common.py
pypolymix/stochastic_model.py
pypolymix/surrogate_models/__init__.py
pypolymix/surrogate_models/base.py
pypolymix/surrogate_models/mixture.py
pypolymix/surrogate_models/neural_network.py
pypolymix/surrogate_models/polynomial_chaos.py
pypolymix-0.1.5.dist-info/METADATA
pypolymix-0.1.5.dist-info/WHEEL
pypolymix-0.1.5.dist-info/licenses/LICENSE
pypolymix-0.1.5.dist-info/RECORD
