Metadata-Version: 2.4
Name: pypolymix
Version: 0.1.5
Summary: A light-weight PyTorch companion for building stochastic surrogate models
License: BSD 3-Clause License
License-File: LICENSE
Keywords: uncertainty quantification,surrogate modeling,pytorch,polynomial chaos expansion,stochastic modeling
Author: pmrobbe
Author-email: pmrobbe@sandia.gov
Requires-Python: >=3.10,<4.0
Classifier: Development Status :: 3 - Alpha
Classifier: Intended Audience :: Science/Research
Classifier: License :: OSI Approved :: BSD License
Classifier: Operating System :: OS Independent
Classifier: Programming Language :: Python :: 3
Classifier: Programming Language :: Python :: 3.10
Classifier: Programming Language :: Python :: 3.11
Classifier: Programming Language :: Python :: 3.12
Classifier: Topic :: Scientific/Engineering :: Artificial Intelligence
Classifier: Topic :: Scientific/Engineering :: Mathematics
Classifier: Topic :: Scientific/Engineering :: Physics
Provides-Extra: dev
Provides-Extra: docs
Provides-Extra: examples
Requires-Dist: ipykernel (>=6.30.1,<7.0.0) ; extra == "examples"
Requires-Dist: matplotlib (>=3.10.6,<4.0.0) ; extra == "examples"
Requires-Dist: mkdocs (>=1.6.1,<2.0.0) ; extra == "docs"
Requires-Dist: mkdocs-jupyter (>=0.25.1,<0.26.0) ; extra == "docs"
Requires-Dist: mkdocs-material (>=9.7.0,<10.0.0) ; extra == "docs"
Requires-Dist: mkdocstrings[python] (>=0.30.1,<0.31.0) ; extra == "docs"
Requires-Dist: papermill (>=2.6.0,<3.0.0) ; extra == "examples"
Requires-Dist: pre-commit (>=4.3.0,<5.0.0) ; extra == "dev"
Requires-Dist: torch (>=2.1.0,<3.0.0)
Project-URL: Documentation, https://sandialabs.github.io/pypolymix
Project-URL: Homepage, https://sandialabs.github.io/pypolymix
Project-URL: Issues, https://github.com/sandialabs/pypolymix/issues
Project-URL: Repository, https://github.com/sandialabs/pypolymix
